setup.py
fakefiles/__init__.py
fakefiles.egg-info/PKG-INFO
fakefiles.egg-info/SOURCES.txt
fakefiles.egg-info/dependency_links.txt
fakefiles.egg-info/top_level.txt