Metadata-Version: 1.0
Name: fakefiles
Version: 1.0.0
Summary: A package to generate files that are not really there, but can be used like normal.
Home-page: UNKNOWN
Author: UNKNOWN
Author-email: UNKNOWN
License: UNKNOWN
Platform: UNKNOWN
